django_pyrepl/__init__.py
django_pyrepl/py.typed
django_pyrepl/management/commands/__init__.py
django_pyrepl/management/commands/shell.py
django_pyrepl-1.0.0.dist-info/METADATA
django_pyrepl-1.0.0.dist-info/WHEEL
django_pyrepl-1.0.0.dist-info/licenses/LICENCE
django_pyrepl-1.0.0.dist-info/RECORD
