Metadata-Version: 2.3
Name: django-pyrepl
Version: 1.0.0
Summary: Use Python 3.13 REPL with Django shell
Author-email: Sasha Matijasic <sasha@selectnull.com>
Classifier: Framework :: Django
Classifier: Programming Language :: Python :: 3.13
Requires-Python: >=3.13
